pyaction/__init__.py
pyaction/cli.py
pyaction/exceptions.py
pyaction/logging.py
pyaction/utils.py
pyaction/action_template/copier.yml
pyaction/action_template/{{action_slug}}/.dockerignore
pyaction/action_template/{{action_slug}}/.env.jinja
pyaction/action_template/{{action_slug}}/.gitignore
pyaction/action_template/{{action_slug}}/Dockerfile.jinja
pyaction/action_template/{{action_slug}}/README.md.jinja
pyaction/action_template/{{action_slug}}/action.yml.jinja
pyaction/action_template/{{action_slug}}/main.py
pyaction/action_template/{{action_slug}}/pyproject.toml.jinja
pyaction/action_template/{{action_slug}}/{% if include_cicd_testing %}.github{% endif %}/workflows/test.yml
pyaction/issues/__init__.py
pyaction/issues/connector.py
pyaction/issues/rendering.py
pyaction/workflow/__init__.py
pyaction/workflow/annotations.py
pyaction/workflow/stream.py
pyaction/workflow/utils.py
pyaction/workflow/wrapper.py
pyaction-0.8.4.dist-info/METADATA
pyaction-0.8.4.dist-info/WHEEL
pyaction-0.8.4.dist-info/entry_points.txt
pyaction-0.8.4.dist-info/licenses/LICENSE
pyaction-0.8.4.dist-info/RECORD
