Metadata-Version: 2.3
Name: pyaction
Version: 0.8.4
Summary: Create GitHub Actions using Python
Project-URL: Documentation, https://pyaction.imsadra.me
Project-URL: Repository, https://github.com/lnxpy/pyaction
Author-email: Sadra Yahyapour <lnxpylnxpy@gmail.com>
License: MIT License
Classifier: Development Status :: 5 - Production/Stable
Classifier: Environment :: Console
Classifier: Intended Audience :: Developers
Classifier: License :: OSI Approved :: MIT License
Classifier: Operating System :: POSIX
Classifier: Programming Language :: Python
Classifier: Programming Language :: Python :: 3 :: Only
Classifier: Programming Language :: Python :: 3.9
Classifier: Programming Language :: Python :: 3.10
Classifier: Programming Language :: Python :: 3.11
Classifier: Programming Language :: Python :: 3.12
Classifier: Programming Language :: Python :: 3.13
Requires-Python: >=3.9
Requires-Dist: pydantic~=2.9.2
Requires-Dist: requests~=2.32.3
Provides-Extra: cli
Requires-Dist: click~=8.1; extra == 'cli'
Requires-Dist: copier~=9.2; extra == 'cli'
Requires-Dist: python-dotenv~=1.0.1; extra == 'cli'
Provides-Extra: dev
Requires-Dist: coverage; extra == 'dev'
Requires-Dist: pytest-cookies; extra == 'dev'
